{"n":15,"variables":[{"id":"GDP_UK","name":"UK Real GDP","transformation":"log","isFinancial":false,"prior":"RW","block":"domestic"},{"id":"CONS_UK","name":"UK Consumption","transformation":"log","isFinancial":false,"prior":"RW","block":"domestic"},{"id":"INV_UK","name":"UK Investment","transformation":"log","isFinancial":false,"prior":"RW","block":"domestic"},{"id":"GOV_UK","name":"UK Gov Spending","transformation":"log","isFinancial":false,"prior":"RW","block":"domestic"},{"id":"EXP_UK","name":"UK Exports","transformation":"log","isFinancial":false,"prior":"RW","block":"domestic"},{"id":"IMP_UK","name":"UK Imports","transformation":"log","isFinancial":false,"prior":"RW","block":"domestic"},{"id":"IP_UK","name":"UK Ind Production Index","transformation":"log","isFinancial":false,"prior":"RW","block":"domestic"},{"id":"LR_UK","name":"UK Unemployment Rate","transformation":"lin","isFinancial":false,"prior":"RW","block":"domestic"},{"id":"CPI_UK","name":"UK CPI Index","transformation":"log","isFinancial":false,"prior":"RW","block":"domestic"},{"id":"RATE_UK","name":"UK 3M Interbank Rate","transformation":"lin","isFinancial":true,"prior":"RW","block":"domestic"},{"id":"YIELD10_UK","name":"UK 10Y Gilt Yield","transformation":"lin","isFinancial":true,"prior":"RW","block":"domestic"},{"id":"NEER_UK","name":"UK NEER","transformation":"log","isFinancial":true,"prior":"RW","block":"domestic"},{"id":"ROWDEM_UK","name":"UK RoW Demand (trade-wtd foreign GDP growth, % q/q ann.)","transformation":"lin","isFinancial":false,"prior":"RW","block":"row"},{"id":"ROWINF_UK","name":"UK RoW Inflation (trade-wtd foreign inflation, % q/q ann.)","transformation":"lin","isFinancial":false,"prior":"RW","block":"row"},{"id":"ROWFIN_UK","name":"UK RoW Short Rate (trade-wtd foreign policy, %)","transformation":"lin","isFinancial":true,"prior":"RW","block":"row"}]}